__init__.py
closure/__init__.py
closure/coherence_times.py
closure/random_scatterers.py
constants/__init__.py
constants/constants.py
io/__init__.py
io/cfg.py
io/netcdf.py
io/raw.py
io/state.py
nrcs/__init__.py
nrcs/ka.py
nrcs/kodis.py
nrcs/romeiser97.py
oceansar/__init__.py
oceansar/closure/__init__.py
oceansar/closure/coherence_times.py
oceansar/closure/random_scatterers.py
oceansar/constants/__init__.py
oceansar/constants/constants.py
oceansar/io/__init__.py
oceansar/io/cfg.py
oceansar/io/netcdf.py
oceansar/io/raw.py
oceansar/io/state.py
oceansar/nrcs/__init__.py
oceansar/nrcs/ka.py
oceansar/nrcs/kodis.py
oceansar/nrcs/romeiser97.py
oceansar/radarsim/__init__.py
oceansar/radarsim/antenna.py
oceansar/radarsim/osiris_sarsim.py
oceansar/radarsim/range_profile.py
oceansar/radarsim/sar_raw.py
oceansar/scatstats/__init__.py
oceansar/scatstats/radar_stats.py
oceansar/spec/__init__.py
oceansar/spec/elfouhaily.py
oceansar/spec/jonswap.py
oceansar/spec/neumann_.py
oceansar/spec/romeiser97.py
oceansar/spread/__init__.py
oceansar/spread/banner.py
oceansar/spread/cos2s.py
oceansar/spread/elfouhaily.py
oceansar/spread/hasselmann80.py
oceansar/spread/mcdaniel.py
oceansar/spread/romeiser97.py
oceansar/spread/swop.py
oceansar/surfaces/__init__.py
oceansar/surfaces/balancer.py
oceansar/surfaces/ocean.py
oceansar/utils/__init__.py
oceansar/utils/geometry.py
oceansar/utils/misc.py
oceansar-16.11.11.dist-info/DESCRIPTION.rst
oceansar-16.11.11.dist-info/METADATA
oceansar-16.11.11.dist-info/RECORD
oceansar-16.11.11.dist-info/WHEEL
oceansar-16.11.11.dist-info/metadata.json
oceansar-16.11.11.dist-info/top_level.txt
radarsim/__init__.py
radarsim/antenna.py
radarsim/osiris_sarsim.py
radarsim/range_profile.py
radarsim/sar_raw.py
scatstats/__init__.py
scatstats/radar_stats.py
spec/__init__.py
spec/elfouhaily.py
spec/jonswap.py
spec/neumann_.py
spec/romeiser97.py
spread/__init__.py
spread/banner.py
spread/cos2s.py
spread/elfouhaily.py
spread/hasselmann80.py
spread/mcdaniel.py
spread/romeiser97.py
spread/swop.py
surfaces/__init__.py
surfaces/balancer.py
surfaces/ocean.py
utils/__init__.py
utils/geometry.py
utils/misc.py
