Metadata-Version: 2.0
Name: oceansar
Version: 16.11.11
Summary: UNKNOWN
Home-page: https://github.com/pakodekker/OCEANSAR
Author: Paco Lopez Dekker
Author-email: F.LopezDekker@tudelft.nl
License: GPL-3.0
Platform: UNKNOWN
Requires-Dist: matplotlib
Requires-Dist: mpi4py
Requires-Dist: numba
Requires-Dist: numexpr
Requires-Dist: numpy
Requires-Dist: scipy
